hiven/__init__.py
hiven/client.py
hiven/data.py
hiven/errors/__init__.py
hiven/errors/base.py
hiven/errors/event.py
hiven/errors/websocket.py
hiven/gateway/__init__.py
hiven/gateway/http.py
hiven/gateway/websocket.py
hiven/types/__init__.py
hiven/types/attachment.py
hiven/types/channel_emoji.py
hiven/types/default_permission_override.py
hiven/types/entity.py
hiven/types/house.py
hiven/types/member.py
hiven/types/message.py
hiven/types/permission_override.py
hiven/types/resource_pointer.py
hiven/types/role.py
hiven/types/room.py
hiven/types/user.py
hiven.py-0.0.3.dist-info/LICENSE
hiven.py-0.0.3.dist-info/WHEEL
hiven.py-0.0.3.dist-info/METADATA
hiven.py-0.0.3.dist-info/RECORD
