Metadata-Version: 2.1
Name: hiven.py
Version: 0.0.3
Summary: 📦 Opensource Python wrapper for Hiven's HTTP and WebSocket API
Home-page: https://github.com/trustedmercury/hiven.py
License: MIT
Author: Kevin Thomas
Author-email: kevin.jt2007@gmail.com
Requires-Python: >=3.9,<4.0
Classifier: License :: OSI Approved :: MIT License
Classifier: Programming Language :: Python :: 3
Classifier: Programming Language :: Python :: 3.9
Requires-Dist: aiohttp (>=3.7.4,<4.0.0)
Project-URL: Repository, https://github.com/trustedmercury/hiven.py
